modsman_gui/__init__.py
modsman_gui/images/icon.png
modsman_gui/main.py
modsman_gui-0.1.0.dist-info/entry_points.txt
modsman_gui-0.1.0.dist-info/WHEEL
modsman_gui-0.1.0.dist-info/METADATA
modsman_gui-0.1.0.dist-info/RECORD
